MANIFEST.in
README.md
requirements.txt
setup.py
py433/__init__.py
py433/client.py
py433/configuration.py
py433/defaults.py
py433/mqtt.py
py433/receiver.py
py433/tcp_server.py
py433/transmitter.py
py433d.egg-info/PKG-INFO
py433d.egg-info/SOURCES.txt
py433d.egg-info/dependency_links.txt
py433d.egg-info/requires.txt
py433d.egg-info/top_level.txt
scripts/433c.py
scripts/433d.py